dataforgetoolkit/__init__.py
dataforgetoolkit/common_utils.py
dataforgetoolkit/datamapper.py
dataforgetoolkit-1.0.6.dist-info/METADATA
dataforgetoolkit-1.0.6.dist-info/WHEEL
dataforgetoolkit-1.0.6.dist-info/top_level.txt
dataforgetoolkit-1.0.6.dist-info/RECORD
