Metadata-Version: 2.1
Name: dataforgetoolkit
Version: 1.0.6
Summary: It is a library that facilitates converting CSV files to various formats (such as DataFrames or other CSV/Excel files) based on a JSON mapping
Home-page: https://github.com/amitsingh7668/dataforgetoolkit
Author: Amit Singh
Author-email: 2singh.amit3@gmail.com
License: Amit Singh
Platform: UNKNOWN
Classifier: Intended Audience :: Developers
Classifier: Programming Language :: Python :: 3
Classifier: Programming Language :: Python :: 3.6
Classifier: Programming Language :: Python :: 3.7
Classifier: Programming Language :: Python :: 3.8
Classifier: Programming Language :: Python :: 3.9
